domias/__init__.py
domias/baselines.py
domias/evaluator.py
domias/version.py
domias/bnaf/__init__.py
domias/bnaf/bnaf.py
domias/bnaf/density_estimation.py
domias/bnaf/optim/__init__.py
domias/bnaf/optim/adam.py
domias/bnaf/optim/adamax.py
domias/bnaf/optim/lr_scheduler.py
domias/metrics/__init__.py
domias/metrics/evaluation.py
domias/metrics/wd.py
domias/models/__init__.py
domias/models/ctgan.py
domias/models/generator.py
domias-0.0.5.dist-info/LICENSE
domias-0.0.5.dist-info/METADATA
domias-0.0.5.dist-info/WHEEL
domias-0.0.5.dist-info/top_level.txt
domias-0.0.5.dist-info/RECORD
