Metadata-Version: 2.1
Name: domias
Version: 0.0.5
Summary: DOMIAS, a density-based MIA model that aims to infer membership by targeting local overfitting of the generative model.
Home-page: https://www.vanderschaar-lab.com/
Author: vanderschaarlab
Author-email: 
License: MIT
Platform: any
Classifier: Programming Language :: Python :: 3
Classifier: Topic :: Scientific/Engineering :: Artificial Intelligence
Classifier: Intended Audience :: Science/Research
Classifier: License :: OSI Approved :: MIT License
Classifier: Operating System :: OS Independent
License-File: LICENSE
Requires-Dist: numpy
Requires-Dist: pandas
Requires-Dist: torch
Requires-Dist: scikit-learn
Requires-Dist: tensorboardX
Requires-Dist: geomloss
Requires-Dist: importlib-metadata ; python_version < "3.8"
Provides-Extra: testing
Requires-Dist: setuptools ; extra == 'testing'
Requires-Dist: pytest ; extra == 'testing'
Requires-Dist: pytest-cov ; extra == 'testing'
Requires-Dist: pre-commit ; extra == 'testing'
Requires-Dist: black ; extra == 'testing'
Requires-Dist: flake8 ; extra == 'testing'
Requires-Dist: jupyter ; extra == 'testing'
Requires-Dist: notebook ; extra == 'testing'
Requires-Dist: isort ; extra == 'testing'
